tgback_x_qt/__init__.py
tgback_x_qt/app.py
tgback_x_qt/defaults.py
tgback_x_qt/helpers.py
tgback_x_qt/version.py
tgback_x_qt/resources/__init__.py
tgback_x_qt/resources/build.py
tgback_x_qt/resources/fonts.qrc
tgback_x_qt/resources/img.qrc
tgback_x_qt/resources/_build/fonts_rc.py
tgback_x_qt/resources/_build/img_rc.py
tgback_x_qt/resources/fonts/inter.ttf
tgback_x_qt/resources/fonts/roboto_mono.ttf
tgback_x_qt/resources/img/loading_spinner.gif
tgback_x_qt/resources/img/no_profile_pic.png
tgback_x_qt/resources/img/telegram.png
tgback_x_qt/resources/img/telegram_tgback_x.png
tgback_x_qt/resources/img/tgback_x.png
tgback_x_qt/stylesheet/bright.qss
tgback_x_qt/stylesheet/dark.qss
tgback_x_qt/ui/account.ui
tgback_x_qt/ui/code.ui
tgback_x_qt/ui/create_backup.ui
tgback_x_qt/ui/create_phrase.ui
tgback_x_qt/ui/input_birthday.ui
tgback_x_qt/ui/open_backup.ui
tgback_x_qt/ui/setup_scrypt.ui
tgback_x_qt/ui/start_screen.ui
tgback_x_qt-0.1.dist-info/LICENSE
tgback_x_qt-0.1.dist-info/METADATA
tgback_x_qt-0.1.dist-info/WHEEL
tgback_x_qt-0.1.dist-info/entry_points.txt
tgback_x_qt-0.1.dist-info/top_level.txt
tgback_x_qt-0.1.dist-info/RECORD
