Metadata-Version: 2.1
Name: tgback-x-qt
Version: 0.1
Summary: Tgback-XQt is a Qt frontend for tgback-X
Home-page: https://github.com/NotStatilko/tgback-x-qt
Download-URL: https://github.com/NotStatilko/tgback-x-qt/archive/refs/tags/v0.1.tar.gz
Author-email: thenonproton@pm.me
License: MIT
License-File: LICENSE
Requires-Dist: tgback-x<2
Requires-Dist: pyside6-essentials==6.8.1
Requires-Dist: darkdetect==0.8.0
Provides-Extra: build
Requires-Dist: pyside6==6.8.1; extra == "build"
